spacy_syllables/__init__.py
spacy_syllables-3.0.2.dist-info/LICENSE
spacy_syllables-3.0.2.dist-info/METADATA
spacy_syllables-3.0.2.dist-info/WHEEL
spacy_syllables-3.0.2.dist-info/top_level.txt
spacy_syllables-3.0.2.dist-info/RECORD
