Metadata-Version: 2.1
Name: spacy-syllables
Version: 3.0.2
Summary: spacy pipeline component for syllables
Author-email: sloev <johannes.valbjorn@gmail.com>
License: Copyright 2020 sloev
Project-URL: Homepage, https://github.com/sloev/spacy-syllables
Keywords: spacy,pyphen,syllable,syllables
Classifier: Development Status :: 6 - Mature
Classifier: Intended Audience :: Developers
Classifier: Natural Language :: English
Classifier: Programming Language :: Python :: 3.6
Classifier: Programming Language :: Python :: 3.7
Classifier: Programming Language :: Python :: 3.8
Classifier: Programming Language :: Python :: 3.9
Classifier: Programming Language :: Python :: 3.10
Classifier: Programming Language :: Python :: 3.11
Requires-Python: >=3.7
License-File: LICENSE
Requires-Dist: spacy (>=3.0.3)
Requires-Dist: pyphen (>=0.10.0)
Provides-Extra: dev
Requires-Dist: black (>=23.1.0) ; extra == 'dev'
Requires-Dist: pytest ; extra == 'dev'
